os_bruteforcer-1.0.2.dist-info/licenses/LICENSE
src/OS_bruteforcer.py
src/__init__.py
src/animation.py
src/assets/__init__.py
src/assets/pass.txt
os_bruteforcer-1.0.2.dist-info/METADATA
os_bruteforcer-1.0.2.dist-info/WHEEL
os_bruteforcer-1.0.2.dist-info/entry_points.txt
os_bruteforcer-1.0.2.dist-info/top_level.txt
os_bruteforcer-1.0.2.dist-info/RECORD
