Metadata-Version: 2.4
Name: OS-BruteForcer
Version: 1.0.2
Summary: A Python automation tool for OS detection and login attempts using nmap, hydra, and xfreerdp/sshpass.
Home-page: https://github.com/cyb2rS2c/OS_BruteForcer
Author: cyb2rS2c
Author-email: 
License: MIT
Classifier: Programming Language :: Python :: 3
Classifier: License :: OSI Approved :: MIT License
Classifier: Operating System :: OS Independent
Requires-Python: >=3.6
License-File: LICENSE
Requires-Dist: colorama
Requires-Dist: termcolor
Requires-Dist: pyfiglet
Requires-Dist: setuptools
Dynamic: author
Dynamic: classifier
Dynamic: description
Dynamic: description-content-type
Dynamic: home-page
Dynamic: license
Dynamic: license-file
Dynamic: requires-dist
Dynamic: requires-python
Dynamic: summary
